llama_index/llms/sambanovasystems/__init__.py
llama_index/llms/sambanovasystems/base.py
llama_index_llms_sambanovasystems-0.5.1.dist-info/METADATA
llama_index_llms_sambanovasystems-0.5.1.dist-info/WHEEL
llama_index_llms_sambanovasystems-0.5.1.dist-info/licenses/LICENSE
llama_index_llms_sambanovasystems-0.5.1.dist-info/RECORD
