Metadata-Version: 2.4
Name: llama-index-llms-sambanovasystems
Version: 0.5.1
Summary: llama-index llms sambanova cloud and sambastudio integration
Author-email: Rodrigo Maldonado <rodrigo.maldonado@pucp.edu.pe>
License-File: LICENSE
Requires-Python: <4.0,>=3.9
Requires-Dist: aiohttp
Requires-Dist: llama-index-core<0.15,>=0.13.0
Requires-Dist: python-dotenv<2,>=1.0.1
